{
  "id": "flame-comics",
  "name": "Flame Comics",
  "author": "Community",
  "description": "Iris Official Source for flamecomics.xyz.",
  "version": "0.1.3",
  "schemaVersion": 1,
  "language": "en",
  "website": "https://flamecomics.xyz",
  "contentRating": "Everyone",
  "repository": "https://github.com/majorxsense-prog/iris-source-repository",
  "installURL": "iris://source/add?repository=https%3A%2F%2Fraw.githubusercontent.com%2Fmajorxsense-prog%2Firis-source-repository%2Fmain%2Frepository.json&source=flame-comics",
  "entry": "source.js",
  "runtime": {
    "kind": "javascript",
    "entry": "source.js",
    "minimumIrisVersion": "0.1.0"
  },
  "capabilities": [
    "CHAPTER_PROVIDING",
    "DISCOVER_SECTION_PROVIDING",
    "SEARCH_RESULT_PROVIDING"
  ]
}
